{"assets/images/.DS_Store":["assets/images/.DS_Store"],"assets/images/apiaceae.png":["assets/images/apiaceae.png"],"assets/images/asteraceae.png":["assets/images/asteraceae.png"],"assets/images/boraginaceae.png":["assets/images/boraginaceae.png"],"assets/images/brassicaceae.png":["assets/images/brassicaceae.png"],"assets/images/caryophyllaceae.png":["assets/images/caryophyllaceae.png"],"assets/images/fabaceae.png":["assets/images/fabaceae.png"],"assets/images/flower_bg.png":["assets/images/flower_bg.png"],"assets/images/flower_fg.png":["assets/images/flower_fg.png"],"assets/images/flower_shadow_ios.png":["assets/images/flower_shadow_ios.png"],"assets/images/flower_web.png":["assets/images/flower_web.png"],"assets/images/lamiaceae.png":["assets/images/lamiaceae.png"],"assets/images/rosaceae.png":["assets/images/rosaceae.png"],"assets/images/wiki_logo.svg":["assets/images/wiki_logo.svg"],"packages/cupertino_icons/assets/CupertinoIcons.ttf":["packages/cupertino_icons/assets/CupertinoIcons.ttf"]}